setup.py
prob_dist_md/Binomialdistribution.py
prob_dist_md/Gaussiandistribution.py
prob_dist_md/Generaldistribution.py
prob_dist_md/__init__.py
prob_dist_md.egg-info/PKG-INFO
prob_dist_md.egg-info/SOURCES.txt
prob_dist_md.egg-info/dependency_links.txt
prob_dist_md.egg-info/not-zip-safe
prob_dist_md.egg-info/top_level.txt