Metadata-Version: 1.0
Name: prob-dist-md
Version: 0.1
Summary: Gaussian and Binomial distributions
Home-page: UNKNOWN
Author: Michael Diggin
Author-email: UNKNOWN
License: UNKNOWN
Platform: UNKNOWN
